.DS_Store
mitten/__init__.py
mitten/diagnostics.py
mitten/helpers.py
mitten/hotelling.py
mitten/mcusum.py
mitten/mewma.py
mitten/plotting.py
mitten-0.1.0.dist-info/METADATA
mitten-0.1.0.dist-info/WHEEL
mitten-0.1.0.dist-info/top_level.txt
mitten-0.1.0.dist-info/RECORD
